vlab_api_common/__init__.py
vlab_api_common/constants.py
vlab_api_common/flask_common.py
vlab_api_common/http_auth.py
vlab_api_common/std_logger.py
vlab_api_common-2020.12.29.dist-info/LICENSE
vlab_api_common-2020.12.29.dist-info/METADATA
vlab_api_common-2020.12.29.dist-info/WHEEL
vlab_api_common-2020.12.29.dist-info/top_level.txt
vlab_api_common-2020.12.29.dist-info/RECORD
