Metadata-Version: 2.1
Name: vlab-api-common
Version: 2020.12.29
Summary: Common logic used by all the RESTful API services of vLab
Home-page: UNKNOWN
Author: Kevin Broadwater, Nicholas Willhite
Author-email: willnx84@gmail.com
License: UNKNOWN
Platform: UNKNOWN
Classifier: Development Status :: 3 - Alpha
Classifier: Intended Audience :: Developers
Classifier: License :: OSI Approved :: Apache Software License
Classifier: Natural Language :: English
Classifier: Operating System :: POSIX :: Linux
Classifier: Programming Language :: Python :: 3.6
Requires-Dist: flask-classy
Requires-Dist: requests
Requires-Dist: pyjwt
Requires-Dist: ujson
Requires-Dist: jsonschema
Requires-Dist: cryptography
Requires-Dist: pyVmomi
